go2scope/__init__.py
go2scope/dataio/__init__.py
go2scope/dataio/g2sdataset/__init__.py
go2scope/dataio/g2sdataset/dataset.py
go2scope/dataio/g2sdataset/reader.py
go2scope/dataio/g2sdataset/writer.py
go2scope-0.0.1.dist-info/LICENCE
go2scope-0.0.1.dist-info/METADATA
go2scope-0.0.1.dist-info/WHEEL
go2scope-0.0.1.dist-info/top_level.txt
go2scope-0.0.1.dist-info/RECORD
