Metadata-Version: 2.1
Name: go2scope
Version: 0.0.1
Summary: go2scope support functions for python: data I/O
Home-page: https://github.com/go2scope/micro-manager-plus/tree/master/python/go2scope
Author: Nenad Amodaj
Author-email: nenad@go2scope.com
License: UNKNOWN
Platform: UNKNOWN
Classifier: Programming Language :: Python :: 3
Classifier: License :: OSI Approved :: MIT License
Classifier: Operating System :: OS Independent
Requires-Python: >=3.7
Requires-Dist: numpy (==1.18.2)
Requires-Dist: opencv-python (==4.2.0.34)
